{
  "source_url": "https://mfmc.ru/catalog/alfa/nasosnye-ustanovki-alfa-dlya-sistem-vodosnabzheniya/",
  "fetched_at": "2026-04-25",
  "title_original": "Насосные установки АЛЬФА Stream® для систем водоснабжения",
  "title_anhel": "Насосные установки ANHEL® HVS-NU для систем водоснабжения",
  "tagline_original": "предназначены для повышения и поддержания постоянного уровня давления или создания необходимого перепада давления",
  "lede_long": "Насосные установки разработаны для повышения давления в системах водоснабжения. Оборудование нивелирует колебания центральной магистрали и гарантирует поддержание заданного напора в трубопроводе. Это предотвращает гидроудары. Станция может быть выполнена на базе многоступенчатых вертикальных, а также консольных и моноблочных горизонтальных насосов.",
  "tech_specs": [
    {"label": "Количество насосов", "value": "от 2 до 6", "unit": "шт. (стандарт)"},
    {"label": "Тип регулирования", "value": "релейное / частотное / частотное на каждый насос (КЧП)", "unit": "с контроллером"},
    {"label": "Макс. температура жидкости", "value": "120", "unit": "°С (по запросу до 180 °С)"},
    {"label": "Сетевое напряжение", "value": "3 × 380", "unit": "В"},
    {"label": "Макс. температура среды", "value": "40", "unit": "°С"},
    {"label": "Мощность одного насоса", "value": "от 0,37 до 90", "unit": "кВт (стандарт)"},
    {"label": "Частота вращения", "value": "2900 / 1450", "unit": "об/мин"},
    {"label": "Макс. давление в системе", "value": "40", "unit": "бар"},
    {"label": "Срок службы", "value": "не менее 10", "unit": "лет"}
  ],
  "applications_raw": [
    "Хозяйственно-питьевое водоснабжение жилых зданий, объектов социально-культурного, бытового и коммерческого назначения",
    "Водоснабжение зданий промышленного назначения для технологических процессов",
    "Системы подачи воды на объектах специализированного назначения",
    "Системы циркуляции, отопления и охлаждения для зданий различного назначения"
  ],
  "advantages_raw": [
    "Профессиональное серийное производство",
    "Индивидуальное исполнение по техническому заданию заказчика",
    "Контроль качества каждой произведенной насосной станции",
    "Многообразие режимов управления насосной станцией",
    "Энергоэффективное исполнение",
    "Гарантия надежности и долгого срока службы",
    "Компактное исполнение, удобство транспортировки и монтажа оборудования",
    "Рекомендации крупнейших заказчиков",
    "Полный комплект разрешительной и эксплуатационной документации"
  ],
  "pumps_brands_raw": "RVP – AquaDeus; CDM – CNP; LVR – Leo; Boosta – ГМС",
  "components_brands_raw": ["DEKraft", "Unitronics", "IEK", "КЭАЗ", "EKF", "CHINT", "DKC", "Weintek", "ТИТАН Контрол"],
  "documents_raw": [
    {"title": "Декларация соответствия на НУ АЛЬФА", "size": "0.08 МБ"},
    {"title": "Сертификат соответствия на ШУ ОМЕГА типа АШУ", "size": "0.87 МБ"},
    {"title": "Руководство по эксплуатации НУ АЛЬФА СПД", "size": "0.81 МБ"}
  ],
  "spheres_extended": "Насосные станции адаптированы для работы в различных сферах. Хозяйственно-питьевое водоснабжение жилых зданий, учреждений социально-культурного, бытового и коммерческого назначения. Стабильное давление, беспрепятственная подача воды и защита от гидроударов в системах водоснабжения многоквартирных или частных домов, коммерческих и промышленных объектов. Установки поддерживают необходимый напор для технологических процессов и других производственных нужд. Специализированные объекты — спортивные комплексы, медицинские учреждения, выставочные центры. Системы циркуляции, отопления и охлаждения зданий различного назначения."
}
